mkl/__init__.py
mkl/_init_helper.py
mkl/_mkl_service.pyx
mkl/_mklinit.cpython-314-x86_64-linux-gnu.so
mkl/_mklinitmodule.c
mkl/_py_mkl_service.cpython-314-x86_64-linux-gnu.so
mkl/_version.py
mkl/tests/test_mkl_service.py
mkl_service-2.6.1.dist-info/licenses/LICENSE.txt
mkl_service-2.6.1.dist-info/METADATA
mkl_service-2.6.1.dist-info/WHEEL
mkl_service-2.6.1.dist-info/top_level.txt
mkl_service-2.6.1.dist-info/RECORD
