Metadata-Version: 2.4
Name: mkl-service
Version: 2.6.1
Summary: Python hooks for Intel® oneAPI Math Kernel Library (oneMKL) runtime control settings
Author-email: Intel Corporation <scripting@intel.com>
License-Expression: BSD-3-Clause
Project-URL: Download, http://github.com/IntelPython/mkl-service
Project-URL: Homepage, http://github.com/IntelPython/mkl-service
Keywords: MKL
Classifier: Development Status :: 5 - Production/Stable
Classifier: Intended Audience :: Science/Research
Classifier: Intended Audience :: Developers
Classifier: Programming Language :: C
Classifier: Programming Language :: Python
Classifier: Programming Language :: Python :: 3
Classifier: Programming Language :: Python :: 3.9
Classifier: Programming Language :: Python :: 3.10
Classifier: Programming Language :: Python :: 3.11
Classifier: Programming Language :: Python :: 3.12
Classifier: Programming Language :: Python :: 3.13
Classifier: Programming Language :: Python :: 3.14
Classifier: Programming Language :: Python :: Implementation :: CPython
Classifier: Topic :: Software Development
Classifier: Topic :: Utilities
Classifier: Operating System :: Microsoft :: Windows
Classifier: Operating System :: POSIX
Classifier: Operating System :: Unix
Requires-Python: <3.15,>=3.9
License-File: LICENSE.txt
Provides-Extra: test
Dynamic: license-file
Requires-Dist: mkl >=2025.3.0,<2026.0a0
